ITPaySDK/__init__.py
ITPaySDK/enums/__init__.py
ITPaySDK/enums/currency.py
ITPaySDK/enums/payment_type.py
ITPaySDK/exceptions.py
ITPaySDK/ITPay.py
itpaysdk-0.2.1.dist-info/LICENSE
itpaysdk-0.2.1.dist-info/METADATA
itpaysdk-0.2.1.dist-info/WHEEL
itpaysdk-0.2.1.dist-info/RECORD
